aihub_deep/utils.py
aihub_deep-1.0.2.dist-info/LICENSE
aihub_deep-1.0.2.dist-info/METADATA
aihub_deep-1.0.2.dist-info/WHEEL
aihub_deep-1.0.2.dist-info/top_level.txt
aihub_deep-1.0.2.dist-info/RECORD
